aiortm/__init__.py
aiortm/__main__.py
aiortm/client.py
aiortm/exceptions.py
aiortm/py.typed
aiortm/cli/__init__.py
aiortm/model/__init__.py
aiortm/model/contacts.py
aiortm/model/response.py
aiortm/model/tasks.py
aiortm/model/timelines.py
aiortm-0.11.0.dist-info/licenses/LICENSE
aiortm-0.11.0.dist-info/METADATA
aiortm-0.11.0.dist-info/WHEEL
aiortm-0.11.0.dist-info/entry_points.txt
aiortm-0.11.0.dist-info/top_level.txt
aiortm-0.11.0.dist-info/RECORD
