Metadata-Version: 2.4
Name: aiortm
Version: 0.11.0
Summary: Use the Remember the Milk API with aiohttp.
Author-email: Martin Hjelmare <marhje52@gmail.com>
License: Apache-2.0
Project-URL: Bug Tracker, https://github.com/MartinHjelmare/aiortm/issues
Project-URL: Changelog, https://github.com/MartinHjelmare/aiortm/blob/main/CHANGELOG.md
Project-URL: repository, https://github.com/MartinHjelmare/aiortm
Classifier: Development Status :: 2 - Pre-Alpha
Classifier: Intended Audience :: Developers
Classifier: Natural Language :: English
Classifier: Operating System :: OS Independent
Classifier: Programming Language :: Python :: 3.12
Classifier: Programming Language :: Python :: 3.13
Classifier: Topic :: Software Development :: Libraries
Requires-Python: >=3.12
License-File: LICENSE
Requires-Dist: aiohttp>=3.8
Requires-Dist: ciso8601>=2.3
Requires-Dist: mashumaro>=3.10
Requires-Dist: yarl>=1.7
Provides-Extra: cli
Requires-Dist: typer<1,>=0.15; extra == "cli"
Dynamic: license-file
